[
  {
    "key": "8-2",
    "bossName": "ブライニクル",
    "clearable": true,
    "searchMode": "ordered-with-dup",
    "checked": 7937,
    "samples": [
      "一一魔一刺",
      "一一魔刺刺",
      "一一魔果刺",
      "一一魔待刺",
      "一一魔搦刺",
      "一一魔玉刺",
      "一一魔強刺",
      "一一魔速刺",
      "一一魔拳刺",
      "一一魔飛刺",
      "一一魔奏刺",
      "一一魔焦刺",
      "一一魔毒刺",
      "一一魔礁刺",
      "一一魔霊刺",
      "一刺魔一刺",
      "一刺魔刺刺",
      "一刺魔果刺",
      "一刺魔待刺",
      "一刺魔搦刺"
    ],
    "pool": "一刺果待搦玉強速拳飛奏焦毒礁霊魔",
    "requireSkills": [],
    "bossIndexes": null,
    "stopReason": "sample-limit"
  }
]