[
  {
    "key": "1-1",
    "bossName": "ルーサー",
    "clearable": true,
    "searchMode": "ordered-with-dup",
    "checked": 20,
    "samples": [
      "一一一待一",
      "一一一待刺",
      "一一一待果",
      "一一一待待",
      "一一一速玉",
      "一一刺待一",
      "一一刺待刺",
      "一一刺待果",
      "一一刺待待",
      "一一刺待玉",
      "一一刺玉待",
      "一一刺強待",
      "一一果待一",
      "一一果待刺",
      "一一果待果",
      "一一果待待",
      "一一待一待",
      "一一待一強",
      "一一待果一",
      "一一待果刺"
    ],
    "pool": "一刺果待搦玉強速",
    "requireSkills": [],
    "bossIndexes": null,
    "stopReason": "sample-limit"
  },
  {
    "key": "1-2",
    "bossName": "肉厚な魚",
    "clearable": true,
    "searchMode": "ordered-with-dup",
    "checked": 20,
    "samples": [
      "一一一玉速",
      "一一一強果",
      "一一一強玉",
      "一一一速玉",
      "一一刺待一",
      "一一刺待刺",
      "一一刺待果",
      "一一刺待待",
      "一一刺待搦",
      "一一刺待玉",
      "一一刺待強",
      "一一刺待速",
      "一一刺玉果",
      "一一刺玉待",
      "一一刺強一",
      "一一果一玉",
      "一一果刺玉",
      "一一果果玉",
      "一一果待玉",
      "一一果搦玉"
    ],
    "pool": "一刺果待搦玉強速",
    "requireSkills": [],
    "bossIndexes": null,
    "stopReason": "sample-limit"
  },
  {
    "key": "2-1",
    "bossName": "血に飢えたジョーズ",
    "clearable": true,
    "searchMode": "ordered-with-dup",
    "checked": 20,
    "samples": [
      "一一一一玉",
      "一一一刺玉",
      "一一一果玉",
      "一一一待玉",
      "一一一玉一",
      "一一一玉刺",
      "一一一玉果",
      "一一一玉待",
      "一一一玉搦",
      "一一一玉玉",
      "一一一玉強",
      "一一一玉速",
      "一一一玉拳",
      "一一一強一",
      "一一一強刺",
      "一一一強果",
      "一一一強待",
      "一一一強搦",
      "一一一強玉",
      "一一一強強"
    ],
    "pool": "一刺果待搦玉強速拳",
    "requireSkills": [],
    "bossIndexes": null,
    "stopReason": "sample-limit"
  },
  {
    "key": "2-2",
    "bossName": "弱者狩りのハゲタカ",
    "clearable": true,
    "searchMode": "ordered-with-dup",
    "checked": 169,
    "samples": [
      "一一一待玉",
      "一一一待速",
      "一一一搦待",
      "一一一玉待",
      "一一一玉玉",
      "拳一一一待",
      "一一玉一待",
      "一一一一玉",
      "拳一一刺待",
      "一一玉刺待",
      "一一一刺玉",
      "拳一一果待",
      "一一玉果待",
      "一一一果玉",
      "拳一一待一",
      "一一玉待一",
      "一一一玉一",
      "拳一一待刺",
      "一一玉待刺",
      "一一一玉刺"
    ],
    "pool": "一刺果待搦玉強速拳",
    "requireSkills": [],
    "bossIndexes": null,
    "stopReason": "sample-limit"
  },
  {
    "key": "3-1",
    "bossName": "デザインド・エッグ号",
    "clearable": true,
    "searchMode": "ordered-with-dup",
    "checked": 30,
    "samples": [
      "一一一一飛",
      "一一一刺飛",
      "一一一果飛",
      "一一一待飛",
      "一一一搦飛",
      "一一一玉飛",
      "一一一強飛",
      "一一一速飛",
      "一一一拳飛",
      "一一一飛飛",
      "刺一一一飛",
      "果一一一飛",
      "待一一一飛",
      "搦一一一飛",
      "玉一一一飛",
      "強一一一飛",
      "速一一一飛",
      "拳一一一飛",
      "飛一一一飛",
      "一刺一一飛"
    ],
    "pool": "一刺果待搦玉強速拳飛",
    "requireSkills": [],
    "bossIndexes": null,
    "stopReason": "sample-limit"
  },
  {
    "key": "3-2",
    "bossName": "エーヴィス",
    "clearable": true,
    "searchMode": "ordered-with-dup",
    "checked": 20,
    "samples": [
      "一待待一速",
      "一待待待一",
      "一待待待刺",
      "一待待搦一",
      "一待待搦刺",
      "一待待玉一",
      "一待待玉刺",
      "一待待強一",
      "一待待強刺",
      "一待待速一",
      "一待待速刺",
      "一待待飛一",
      "一待待飛刺",
      "一待搦一速",
      "一待搦待一",
      "一待搦待刺",
      "一待搦搦一",
      "一待搦搦刺",
      "一待搦玉一",
      "一待搦玉刺"
    ],
    "pool": "一刺果待搦玉強速拳飛",
    "requireSkills": [],
    "bossIndexes": null,
    "stopReason": "sample-limit"
  },
  {
    "key": "4-1",
    "bossName": "ラ・マンチャ号",
    "clearable": true,
    "searchMode": "ordered-with-dup",
    "checked": 27,
    "samples": [
      "一一一待一",
      "一一一待刺",
      "一一一待果",
      "一一一待待",
      "一一一待玉",
      "一一一待拳",
      "一一一玉果",
      "一一一玉待",
      "一一一玉拳",
      "一一一強待",
      "一一果待一",
      "一一果待刺",
      "一一果待果",
      "刺一一待一",
      "果一一待一",
      "待一一待一",
      "搦一一待一",
      "玉一一待一",
      "強一一待一",
      "速一一待一"
    ],
    "pool": "一刺果待搦玉強速拳飛奏",
    "requireSkills": [],
    "bossIndexes": null,
    "stopReason": "sample-limit"
  },
  {
    "key": "4-2",
    "bossName": "イスパニア艦隊",
    "clearable": true,
    "searchMode": "ordered-with-dup",
    "checked": 156,
    "samples": [
      "一一一待待",
      "一一一待搦",
      "一一一待玉",
      "一一一搦待",
      "一一一搦飛",
      "一一一玉待",
      "刺一一待待",
      "果一一待待",
      "待一一待待",
      "搦一一待待",
      "玉一一待待",
      "強一一待待",
      "速一一待待",
      "拳一一待待",
      "飛一一待待",
      "奏一一待待",
      "一刺一待待",
      "一果一待待",
      "一待一待待",
      "一搦一待待"
    ],
    "pool": "一刺果待搦玉強速拳飛奏",
    "requireSkills": [],
    "bossIndexes": null,
    "stopReason": "sample-limit"
  },
  {
    "key": "5-1",
    "bossName": "ゾルゲイド",
    "clearable": true,
    "searchMode": "ordered-with-dup",
    "checked": 20,
    "samples": [
      "一一一玉速",
      "一一刺玉速",
      "一一果玉速",
      "一一待玉速",
      "一一搦玉速",
      "一一搦速飛",
      "一一玉玉速",
      "一一強玉速",
      "一一速玉速",
      "一一拳玉速",
      "一一飛玉速",
      "一一奏玉速",
      "一一焦玉速",
      "一刺一玉速",
      "一刺刺玉速",
      "一刺果玉速",
      "一刺待玉速",
      "一刺搦玉速",
      "一刺搦速飛",
      "一刺玉玉速"
    ],
    "pool": "一刺果待搦玉強速拳飛奏焦",
    "requireSkills": [],
    "bossIndexes": null,
    "stopReason": "sample-limit"
  },
  {
    "key": "5-2",
    "bossName": "エルダゾルゲイド",
    "clearable": true,
    "searchMode": "ordered-with-dup",
    "checked": 20,
    "samples": [
      "一一一一果",
      "一一一果果",
      "一一一待果",
      "一一一搦果",
      "一一一玉果",
      "一一一強果",
      "一一一速果",
      "一一一拳果",
      "一一一飛果",
      "一一一焦果",
      "一一刺一果",
      "一一刺果果",
      "一一刺待果",
      "一一刺搦果",
      "一一刺玉果",
      "一一刺強果",
      "一一刺速果",
      "一一刺拳果",
      "一一刺飛果",
      "一一刺焦果"
    ],
    "pool": "一刺果待搦玉強速拳飛奏焦",
    "requireSkills": [],
    "bossIndexes": null,
    "stopReason": "sample-limit"
  },
  {
    "key": "6-1",
    "bossName": "クラーケン",
    "clearable": true,
    "searchMode": "ordered-with-dup",
    "checked": 20,
    "samples": [
      "一一一玉一",
      "一一一玉刺",
      "一一一玉果",
      "一一一玉待",
      "一一一玉搦",
      "一一一玉玉",
      "一一一玉強",
      "一一一玉速",
      "一一一玉飛",
      "一一一拳玉",
      "一一一拳強",
      "一一刺玉一",
      "一一刺玉刺",
      "一一刺玉果",
      "一一刺玉待",
      "一一刺玉搦",
      "一一刺玉玉",
      "一一刺玉強",
      "一一刺玉速",
      "一一刺玉飛"
    ],
    "pool": "一刺果待搦玉強速拳飛奏焦毒",
    "requireSkills": [],
    "bossIndexes": null,
    "stopReason": "sample-limit"
  },
  {
    "key": "6-2",
    "bossName": "ゴルゾアの胃袋",
    "clearable": true,
    "searchMode": "ordered-with-dup",
    "checked": 20,
    "samples": [
      "一一玉待毒",
      "一刺玉待毒",
      "一果玉待毒",
      "一待玉待毒",
      "一搦待待毒",
      "一玉玉待毒",
      "一強玉待毒",
      "一拳玉待毒",
      "一飛玉待毒",
      "一奏玉待毒",
      "一焦玉待毒",
      "一毒玉待毒",
      "刺一玉待毒",
      "刺刺玉待毒",
      "刺果玉待毒",
      "刺待玉待毒",
      "刺搦待待毒",
      "刺玉玉待毒",
      "刺強玉待毒",
      "刺拳玉待毒"
    ],
    "pool": "一刺果待搦玉強速拳飛奏焦毒",
    "requireSkills": [],
    "bossIndexes": null,
    "stopReason": "sample-limit"
  },
  {
    "key": "7-1",
    "bossName": "バクバク",
    "clearable": true,
    "searchMode": "ordered-with-dup",
    "checked": 20,
    "samples": [
      "待刺強一狼",
      "待刺強刺狼",
      "待刺強果狼",
      "待刺強待狼",
      "待刺強搦狼",
      "待刺強玉狼",
      "待刺強強狼",
      "待刺強速狼",
      "待刺強拳狼",
      "待刺強飛狼",
      "待刺強奏狼",
      "待刺強焦狼",
      "待刺強毒狼",
      "待刺強礁狼",
      "待待待刺待",
      "待待待毒一",
      "待待待毒刺",
      "待待待毒果",
      "待待待毒待",
      "待待待毒搦"
    ],
    "pool": "一刺果待搦玉強速拳飛奏焦毒礁狼",
    "requireSkills": [],
    "bossIndexes": null,
    "stopReason": "sample-limit"
  },
  {
    "key": "7-2",
    "bossName": "死者の群れ",
    "clearable": true,
    "searchMode": "ordered-with-dup",
    "checked": 20,
    "samples": [
      "待待待待▽",
      "待待待搦▽",
      "待待待玉▽",
      "待待待強▽",
      "待待待速▽",
      "待待待飛▽",
      "待待待礁▽",
      "待待待▽一",
      "待待待▽刺",
      "待待待▽果",
      "待待待▽待",
      "待待待▽搦",
      "待待待▽玉",
      "待待待▽強",
      "待待待▽速",
      "待待待▽拳",
      "待待待▽飛",
      "待待待▽奏",
      "待待待▽焦",
      "待待待▽毒"
    ],
    "pool": "一刺果待搦玉強速拳飛奏焦毒礁▽",
    "requireSkills": [],
    "bossIndexes": null,
    "stopReason": "sample-limit"
  },
  {
    "key": "8-1",
    "bossName": "死霊船 黒潮号",
    "clearable": true,
    "searchMode": "ordered-with-dup",
    "checked": 20,
    "samples": [
      "一一一待爆",
      "一一一搦爆",
      "一一一玉爆",
      "一一一強爆",
      "一一一速爆",
      "一一一飛爆",
      "一一一礁爆",
      "一一一爆強",
      "一一刺待爆",
      "一一刺搦爆",
      "一一刺玉爆",
      "一一刺強爆",
      "一一刺速爆",
      "一一刺飛爆",
      "一一刺礁爆",
      "一一刺爆強",
      "一一果待爆",
      "一一果搦爆",
      "一一果玉爆",
      "一一果強爆"
    ],
    "pool": "一刺果待搦玉強速拳飛奏焦毒礁霊爆",
    "requireSkills": [],
    "bossIndexes": null,
    "stopReason": "sample-limit"
  },
  {
    "key": "8-2",
    "bossName": "ブライニクル",
    "clearable": true,
    "searchMode": "ordered-with-dup",
    "checked": 20,
    "samples": [
      "一一一強果",
      "一一刺刺果",
      "一一刺刺強",
      "一一刺果一",
      "一一刺果果",
      "一一刺果待",
      "一一刺果搦",
      "一一刺果玉",
      "一一刺果強",
      "一一刺果速",
      "一一刺果拳",
      "一一刺果飛",
      "一一刺果毒",
      "一一刺果礁",
      "一一刺待果",
      "刺一一強果",
      "果一一強果",
      "待一一強果",
      "搦一一強果",
      "玉一一強果"
    ],
    "pool": "一刺果待搦玉強速拳飛奏焦毒礁霊魔",
    "requireSkills": [],
    "bossIndexes": null,
    "stopReason": "sample-limit"
  },
  {
    "key": "9-1",
    "bossName": "廃都の守護者",
    "clearable": true,
    "searchMode": "ordered-with-dup",
    "checked": 20,
    "samples": [
      "一刺一搦飛",
      "一刺一玉狼",
      "一刺刺搦飛",
      "一刺刺玉狼",
      "一刺果搦飛",
      "一刺果玉狼",
      "一刺待搦飛",
      "一刺待玉狼",
      "一刺搦一飛",
      "一刺搦刺飛",
      "一刺搦果飛",
      "一刺搦待待",
      "一刺搦待飛",
      "一刺搦待狼",
      "一刺搦待▽",
      "一刺搦待爆",
      "一刺搦搦飛",
      "一刺搦玉飛",
      "一刺搦強飛",
      "一刺搦速飛"
    ],
    "pool": "一刺果待搦玉強速拳飛奏焦毒礁狼▽霊爆魔円",
    "requireSkills": [],
    "bossIndexes": null,
    "stopReason": "sample-limit"
  },
  {
    "key": "9-2",
    "bossName": "深海の賢王 ジズ",
    "clearable": true,
    "searchMode": "ordered-with-dup",
    "checked": 3548,
    "samples": [
      "礁一飛礁狼",
      "一礁飛礁狼",
      "礁一礁飛狼",
      "一礁礁飛狼",
      "礁刺飛礁狼",
      "礁刺礁飛狼",
      "一速霊玉狼",
      "奏速霊待▽",
      "一速霊玉▽",
      "礁飛一礁狼",
      "一飛礁礁狼",
      "刺礁飛礁狼",
      "果礁飛礁狼",
      "毒礁飛礁狼",
      "礁毒飛礁狼",
      "飛一礁礁狼",
      "霊一飛玉狼",
      "一霊飛玉狼",
      "一一霊玉狼",
      "刺礁礁飛狼"
    ],
    "pool": "一刺果待搦玉強速拳飛奏焦毒礁狼▽霊爆魔円",
    "requireSkills": [],
    "bossIndexes": null,
    "stopReason": "sample-limit"
  },
  {
    "key": "10-1",
    "bossName": "ゾルゲイドクイーン",
    "clearable": true,
    "searchMode": "ordered-with-dup",
    "checked": 20,
    "samples": [
      "一一搦刺飛",
      "一一搦果▽",
      "一一搦待拳",
      "一一搦待▽",
      "一一搦搦▽",
      "一一搦玉▽",
      "一一搦飛▽",
      "一一搦▽飛",
      "一一搦滅▽",
      "一一玉速狼",
      "一一玉礁狼",
      "一刺搦刺飛",
      "一刺搦果▽",
      "一刺搦待拳",
      "一刺搦待▽",
      "一刺搦搦▽",
      "一刺搦玉▽",
      "一刺搦飛▽",
      "一刺搦▽飛",
      "一刺搦滅▽"
    ],
    "pool": "一刺果待搦玉強速拳飛奏焦毒礁狼▽霊爆魔円滅",
    "requireSkills": [],
    "bossIndexes": null,
    "stopReason": "sample-limit"
  },
  {
    "key": "10-2",
    "bossName": "デザインド・エッグ号",
    "clearable": true,
    "searchMode": "ordered-with-dup",
    "checked": 40,
    "samples": [
      "一一搦飛狼",
      "一刺搦飛狼",
      "刺一搦飛狼",
      "果一搦飛狼",
      "待一搦飛狼",
      "搦一搦飛狼",
      "玉一搦飛狼",
      "強一搦飛狼",
      "速一搦飛狼",
      "拳一搦飛狼",
      "飛一搦飛狼",
      "毒一搦飛狼",
      "礁一搦飛狼",
      "霊一搦飛狼",
      "円一搦飛狼",
      "滅一搦飛狼",
      "一果搦飛狼",
      "一待搦飛狼",
      "一搦搦飛狼",
      "一玉搦飛狼"
    ],
    "pool": "一刺果待搦玉強速拳飛奏焦毒礁狼▽霊爆魔円滅",
    "requireSkills": [],
    "bossIndexes": null,
    "stopReason": "sample-limit"
  },
  {
    "key": "11-1",
    "bossName": "エーヴィス海賊団",
    "clearable": true,
    "searchMode": "ordered-with-dup",
    "checked": 20,
    "samples": [
      "一強一霊果",
      "一強一霊狼",
      "一強刺霊果",
      "一強刺霊狼",
      "一強果霊果",
      "一強果霊狼",
      "一強待霊果",
      "一強待霊狼",
      "一強搦霊果",
      "一強搦霊狼",
      "一強玉霊果",
      "一強玉霊狼",
      "一強強霊果",
      "一強強霊狼",
      "一強速霊果",
      "一強速霊狼",
      "一強拳霊果",
      "一強拳霊狼",
      "一強飛霊果",
      "一強飛霊狼"
    ],
    "pool": "一刺果待搦玉強速拳飛奏焦毒礁狼霊円滅受",
    "requireSkills": [],
    "bossIndexes": null,
    "stopReason": "sample-limit"
  },
  {
    "key": "11-2",
    "bossName": "大海賊 エーヴィス",
    "clearable": true,
    "searchMode": "ordered-with-dup",
    "checked": 2414448,
    "samples": [
      "待一礁礁玉",
      "待刺礁礁玉",
      "待果礁礁玉",
      "待待礁礁玉",
      "待搦礁礁玉",
      "待玉礁礁玉",
      "待強礁礁玉",
      "待速礁礁玉",
      "待拳礁礁玉",
      "待飛礁礁玉",
      "待毒礁礁玉",
      "待礁礁礁玉",
      "待円礁礁玉",
      "待滅礁礁玉",
      "待受礁礁玉",
      "霊礁礁玉速"
    ],
    "pool": "一刺果待搦玉強速拳飛奏焦毒礁霊魔円滅受",
    "requireSkills": [],
    "bossIndexes": null,
    "stopReason": "exhausted"
  },
  {
    "key": "12-1",
    "bossName": "偽聖女 リザベル",
    "clearable": true,
    "searchMode": "ordered-with-dup",
    "checked": 20,
    "samples": [
      "一一礁受▽",
      "一刺礁受▽",
      "一果礁受▽",
      "一待礁受▽",
      "一搦礁受▽",
      "一玉礁受▽",
      "一速礁受▽",
      "一拳礁受▽",
      "一飛礁受▽",
      "一奏礁受▽",
      "一焦礁受▽",
      "一毒礁受▽",
      "一礁礁受▽",
      "一滅礁受▽",
      "一受礁受▽",
      "一死礁受▽",
      "刺一礁受▽",
      "刺刺礁受▽",
      "刺果礁受▽",
      "刺待礁受▽"
    ],
    "pool": "一刺果待搦玉強速拳飛奏焦毒礁狼▽霊爆魔円滅受死",
    "requireSkills": [],
    "bossIndexes": null,
    "stopReason": "sample-limit"
  },
  {
    "key": "12-2#1",
    "bossName": "魔女 グリザーベルク",
    "clearable": true,
    "searchMode": "ordered-with-dup",
    "checked": 2672,
    "samples": [
      "一一刺礁飛",
      "一一礁待飛",
      "一一礁搦飛",
      "一一礁玉飛",
      "一一礁強飛",
      "一一礁速飛",
      "一一刺飛礁",
      "一一礁飛待",
      "一一礁飛搦",
      "一一礁飛玉",
      "一一礁飛強",
      "一一礁飛速",
      "一一礁飛飛",
      "一一礁飛焦",
      "毒礁刺一飛",
      "礁毒刺一飛",
      "毒一礁一飛",
      "果一刺礁飛",
      "待一刺礁飛",
      "搦一刺礁飛"
    ],
    "pool": "一刺果待搦玉強速拳飛奏焦毒礁狼▽霊爆魔円滅受死",
    "requireSkills": [],
    "bossIndexes": [
      1
    ],
    "stopReason": "sample-limit"
  },
  {
    "key": "12-2#2",
    "bossName": "魔女 グリザーベルク",
    "clearable": true,
    "searchMode": "ordered-with-dup",
    "checked": 21,
    "samples": [
      "一一果一狼",
      "一一果刺狼",
      "一一果果狼",
      "一一果待狼",
      "一一果搦狼",
      "一一果玉狼",
      "一一果速狼",
      "一一果拳狼",
      "一一果飛狼",
      "一一果奏狼",
      "一一果焦狼",
      "一一果毒狼",
      "一一果礁狼",
      "一一果円狼",
      "一一果滅狼",
      "一一果受狼",
      "一一果死狼",
      "一一奏果狼",
      "一一霊滅狼",
      "刺一果一狼"
    ],
    "pool": "一刺果待搦玉強速拳飛奏焦毒礁狼▽霊爆魔円滅受死",
    "requireSkills": [],
    "bossIndexes": [
      2
    ],
    "stopReason": "sample-limit"
  },
  {
    "key": "12-2#3",
    "bossName": "魔女 グリザーベルク",
    "clearable": true,
    "searchMode": "ordered-with-dup",
    "checked": 20,
    "samples": [
      "一刺搦果飛",
      "一刺搦待果",
      "一刺搦搦果",
      "一刺搦玉果",
      "一刺搦飛果",
      "一刺搦受果",
      "一刺玉速果",
      "一刺玉速狼",
      "一刺玉礁果",
      "一待待果強",
      "一待待待果",
      "一待待搦果",
      "一待待玉果",
      "一待待強果",
      "一待待速果",
      "一待待飛果",
      "一待待礁果",
      "一待待円果",
      "一待待受果",
      "一待搦果強"
    ],
    "pool": "一刺果待搦玉強速拳飛奏焦毒礁狼▽霊爆魔円滅受死",
    "requireSkills": [],
    "bossIndexes": [
      3
    ],
    "stopReason": "sample-limit"
  },
  {
    "key": "12-3",
    "bossName": "魔女 グリザーベルク",
    "clearable": true,
    "searchMode": "ordered-with-dup",
    "checked": 20,
    "samples": [
      "搦飛霊魔死",
      "搦飛魔霊死",
      "搦飛魔死霊",
      "搦霊飛魔死",
      "搦霊魔飛死",
      "搦霊魔死飛",
      "搦魔飛霊死",
      "搦魔飛死霊",
      "搦魔霊飛死",
      "搦魔霊死飛",
      "搦魔死飛霊",
      "搦魔死霊飛",
      "飛礁霊魔死",
      "飛礁魔霊死",
      "飛礁魔死霊",
      "飛霊礁魔死",
      "飛霊魔礁死",
      "飛霊魔死礁",
      "飛魔礁霊死",
      "飛魔礁死霊"
    ],
    "pool": "一刺果待搦玉強速拳飛奏焦毒礁狼▽霊爆魔円滅受死",
    "requireSkills": [],
    "bossIndexes": null,
    "stopReason": "sample-limit"
  }
]